{
  "id": 87,
  "name": "Alpha Pop",
  "tagline": "Hoppy Rye Pale Ale.",
  "first_brewed": "03/2014",
  "description": "A hoppy Rye Ale loaded with an avalanche of citrus and resinous flavours. Columbus, our high-alpha friend, lends a huge pithy citrus blast, with Ahtanum providing a punchy tropical fruit back-up. Brewing with rye adds a spiciness to the speciality malt caramel backbone, giving a warm ginger snap flavour, before slowly the hops, barley and rye combine and build to an orangey, biscuity, almost chocolatey crescendo.",
  "image_url": "https://images.punkapi.com/v2/87.png",
  "abv": 4.5,
  "ibu": 30,
  "target_fg": 1011,
  "target_og": 1045,
  "ebc": 25,
  "srm": 12.5,
  "ph": 4.4,
  "attenuation_level": 75.6,
  "volume": {
    "value": 20,
    "unit": "litres"
  },
  "boil_volume": {
    "value": 25,
    "unit": "litres"
  },
  "method": {
    "mash_temp": [
      {
        "temp": {
          "value": 65,
          "unit": "celsius"
        },
        "duration": null
      }
    ],
    "fermentation": {
      "temp": {
        "value": 19,
        "unit": "celsius"
      }
    },
    "twist": null
  },
  "ingredients": {
    "malt": [
      {
        "name": "Extra Pale",
        "amount": {
          "value": 3.69,
          "unit": "kilograms"
        }
      },
      {
        "name": "Caramalt",
        "amount": {
          "value": 0.16,
          "unit": "kilograms"
        }
      },
      {
        "name": "Dark Crystal",
        "amount": {
          "value": 0.06,
          "unit": "kilograms"
        }
      },
      {
        "name": "Rye",
        "amount": {
          "value": 0.31,
          "unit": "kilograms"
        }
      }
    ],
    "hops": [
      {
        "name": "Columbus",
        "amount": {
          "value": 5,
          "unit": "grams"
        },
        "add": "start",
        "attribute": "bitter"
      },
      {
        "name": "Columbus",
        "amount": {
          "value": 7.5,
          "unit": "grams"
        },
        "add": "middle",
        "attribute": "flavour"
      },
      {
        "name": "Ahtanum",
        "amount": {
          "value": 12.5,
          "unit": "grams"
        },
        "add": "middle",
        "attribute": "flavour"
      },
      {
        "name": "Ahtanum",
        "amount": {
          "value": 37.5,
          "unit": "grams"
        },
        "add": "end",
        "attribute": "flavour"
      },
      {
        "name": "Ahtanum",
        "amount": {
          "value": 125,
          "unit": "grams"
        },
        "add": "dry hop",
        "attribute": "aroma"
      },
      {
        "name": "Columbus",
        "amount": {
          "value": 125,
          "unit": "grams"
        },
        "add": "dry hop",
        "attribute": "aroma"
      }
    ],
    "yeast": "Wyeast 1056 - American Ale™"
  },
  "food_pairing": [
    "Spicy lamb tikka masala",
    "Spicy beef and Mexican black bean burger",
    "Poached cinnamon apple muffins"
  ],
  "brewers_tips": "Columbus and Ahtanum hop additions create a perfect blend of resin and lemon character.",
  "contributed_by": "Sam Mason <samjbmason>"
}
